ai_bundle/__init__.py
ai_bundle/app.py
ai_bundle/main.py
ai_bundle-0.1.1.dist-info/LICENSE
ai_bundle-0.1.1.dist-info/WHEEL
ai_bundle-0.1.1.dist-info/METADATA
ai_bundle-0.1.1.dist-info/RECORD
